MANIFEST.in
README.md
setup.py
src/_cffi_src/__init__.py
src/_cffi_src/trivium_build.py
src/_cffi_src/c-trivium/trivium.c
src/_cffi_src/c-trivium/trivium.h
src/pytrivium/__init__.py
src/pytrivium/trivium.py
src/pytrivium/trivium_old.py
src/pytrivium.egg-info/PKG-INFO
src/pytrivium.egg-info/SOURCES.txt
src/pytrivium.egg-info/dependency_links.txt
src/pytrivium.egg-info/not-zip-safe
src/pytrivium.egg-info/requires.txt
src/pytrivium.egg-info/top_level.txt
src/pytrivium/bindings/__init__.py
tests/demo.py