Metadata-Version: 2.1
Name: pytrivium
Version: 1.0.7
Summary: Python bindings to a C implementation of Trivium
Home-page: https://github.com/rbrenaget/trivium-sw/pytrivium
Author: Romain Brenaget
License: MIT
Platform: UNKNOWN
Classifier: Natural Language :: English
Classifier: Programming Language :: Python :: 3
Classifier: License :: OSI Approved :: MIT License
Classifier: Operating System :: POSIX :: Linux
Classifier: Topic :: Security :: Cryptography
Requires-Python: >=3.6
